deployv/__init__.py
deployv/base/__init__.py
deployv/base/clonev.py
deployv/base/commandv.py
deployv/base/dockerv.py
deployv/base/errors.py
deployv/base/extensions_core.py
deployv/base/nginxv.py
deployv/base/postgresv.py
deployv/base/update_production.py
deployv/base/worker.py
deployv/commands/__init__.py
deployv/commands/deployvcmd.py
deployv/commands/updatev.py
deployv/commands/workerv.py
deployv/extensions/__init__.py
deployv/extensions/checkers.py
deployv/helpers/__init__.py
deployv/helpers/backup.py
deployv/helpers/build_helper.py
deployv/helpers/clone_oca_dependencies.py
deployv/helpers/configuration_helper.py
deployv/helpers/container.py
deployv/helpers/database_helper.py
deployv/helpers/decompress_helper.py
deployv/helpers/git_helper.py
deployv/helpers/json_helper.py
deployv/helpers/pg_anon.py
deployv/helpers/sender_message.py
deployv/helpers/utils.py
deployv/helpers/json_schemas/base.json
deployv/helpers/json_schemas/deploy_deploy.json
deployv/instance/__init__.py
deployv/instance/instancev.py
deployv/messaging/__init__.py
deployv/messaging/basemsg.py
deployv/messaging/http/__init__.py
deployv/messaging/http/httpv.py
deployv/messaging/http/receiverv.py
deployv/messaging/http/senderv.py
deployv/messaging/http/worker.py
deployv/messaging/rabbit/__init__.py
deployv/messaging/rabbit/rabbitv.py
deployv/messaging/rabbit/receiverv.py
deployv/messaging/rabbit/senderv.py
deployv/messaging/rabbit/worker.py
deployv-0.9.221.dist-info/AUTHORS.rst
deployv-0.9.221.dist-info/LICENSE
deployv-0.9.221.dist-info/METADATA
deployv-0.9.221.dist-info/WHEEL
deployv-0.9.221.dist-info/entry_points.txt
deployv-0.9.221.dist-info/top_level.txt
deployv-0.9.221.dist-info/RECORD
