Metadata-Version: 2.1
Name: deployv
Version: 0.9.221
Summary: Base for all clases and scripts in VauxooTools
Home-page: https://git.vauxoo.com/deployv/deployv
Download-URL: https://git.vauxoo.com/deployv/deployv
Author: Tulio Ruiz
Author-email: tulio@vauxoo.com
License: BSD
Keywords: vauxootools deployv
Classifier: Development Status :: 2 - Pre-Alpha
Classifier: Intended Audience :: Developers
Classifier: License :: OSI Approved :: BSD License
Classifier: Natural Language :: English
Classifier: Programming Language :: Python :: 3
Classifier: Programming Language :: Python :: 3.3
Classifier: Programming Language :: Python :: 3.4
Classifier: Programming Language :: Python :: 3.5
Classifier: Programming Language :: Python :: 3.6
Classifier: Programming Language :: Python :: 3.7
License-File: LICENSE
License-File: AUTHORS.rst
Requires-Dist: pika==1.1.0
Requires-Dist: jsonschema==2.6.0
Requires-Dist: branchesv
Requires-Dist: extend-me==1.1.3
Requires-Dist: passlib==1.6.5
Requires-Dist: retry-decorator==1.1.0
Requires-Dist: transitions==0.6.8
Requires-Dist: deployv-static
Requires-Dist: requests-unixsocket==0.2.0
Requires-Dist: jinja2==2.10.1; python_version < "3.7"
Requires-Dist: pyyaml==3.12; python_version < "3.7"
Requires-Dist: PyGithub==1.39; python_version < "3.7"
Requires-Dist: urllib3==1.24.3; python_version < "3.8"
Requires-Dist: requests==2.20.0; python_version < "3.8"
Requires-Dist: cryptography==2.1.4; python_version < "3.8"
Requires-Dist: deepdiff==3.3.0; python_version < "3.9"
Requires-Dist: ipaddress==1.0.23; python_version <= "2.7"
Requires-Dist: psycopg2==2.8.6; python_version <= "3.11"
Requires-Dist: docker==3.3.0; python_version <= "3.4"
Requires-Dist: docker==3.5.1; python_version > "3.4" and python_version < "3.6"
Requires-Dist: psycopg2==2.9.10; python_version >= "3.12"
Requires-Dist: docker==5.0.3; python_version >= "3.6" and python_version < "3.8"
Requires-Dist: jinja2==3.0.3; python_version >= "3.7"
Requires-Dist: pyyaml==5.3.1; python_version >= "3.7"
Requires-Dist: PyGithub==1.55; python_version >= "3.7"
Requires-Dist: markupsafe==2.0.1; python_version >= "3.7"
Requires-Dist: urllib3==1.26.0; python_version >= "3.8"
Requires-Dist: docker==6.0.0; python_version >= "3.8"
Requires-Dist: cryptography==3.4.8; python_version >= "3.8"
Requires-Dist: requests==2.26.0; python_version >= "3.8" and python_version < "3.9"
Requires-Dist: requests==2.31.0; python_version >= "3.9"
Requires-Dist: deepdiff==5.8.1; python_version >= "3.9"
